.mica_settings
.project
.pydevproject
MANIFEST.in
ez_setup.py
setup.cfg
setup.py
.settings/org.eclipse.core.resources.prefs
hildon/pyjama.desktop
hildon/icons/48x48/pyjama.png
hildon/icons/64x64/pyjama.png
media/pyjama.png
scripts/pyjama
src/pyjama/__init__.py
src/pyjama/bootstrap.py
src/pyjama/pyjama-logo.png
src/pyjama.egg-info/PKG-INFO
src/pyjama.egg-info/SOURCES.txt
src/pyjama.egg-info/dependency_links.txt
src/pyjama.egg-info/not-zip-safe
src/pyjama.egg-info/requires.txt
src/pyjama.egg-info/top_level.txt
src/pyjama/common/__init__.py
src/pyjama/common/version.py
src/pyjama/core/__init__.py
src/pyjama/core/exceptions.py
src/pyjama/core/facade.py
src/pyjama/core/model.py
src/pyjama/core/template/default/MANIFEST.in
src/pyjama/core/template/default/ez_setup.py
src/pyjama/core/template/default/setup.cfg
src/pyjama/core/template/default/setup.py
src/pyjama/core/template/default/hildon/pyjama.desktop
src/pyjama/core/template/default/hildon/icons/48x48/pyjama.png
src/pyjama/core/template/default/hildon/icons/64x64/pyjama.png
src/pyjama/core/template/default/media/pyjama.png
src/pyjama/core/template/default/scripts/pyjama
src/pyjama/core/template/default/src/pyjama/__init__.py
src/pyjama/core/template/default/src/pyjama/bootstrap.py
src/pyjama/core/template/default/src/pyjama/pyjama-logo.png
src/pyjama/core/template/default/src/pyjama/common/__init__.py
src/pyjama/core/template/default/src/pyjama/common/version.py
src/pyjama/core/template/default/src/pyjama/core/__init__.py
src/pyjama/core/template/default/src/pyjama/core/exceptions.py
src/pyjama/core/template/default/src/pyjama/core/facade.py
src/pyjama/core/template/default/src/pyjama/core/model.py
src/pyjama/core/template/default/src/pyjama/gui/__init__.py
src/pyjama/core/template/default/src/pyjama/gui/gtk/__init__.py
src/pyjama/core/template/default/src/pyjama/gui/gtk/utils.py
src/pyjama/core/template/default/src/pyjama/gui/gtk/widget.py
src/pyjama/core/template/default/src/pyjama/gui/hildon/__init__.py
src/pyjama/core/template/default/src/pyjama/gui/hildon/portrait.py
src/pyjama/core/template/default/src/pyjama/gui/hildon/pyjamaGui.py
src/pyjama/core/template/default/src/pyjama/gui/hildon/utils.py
