Metadata-Version: 1.0
Name: pyjama
Version: 0.1.0dev-r23
Summary: Pyjama is a python project bootstraper for Maemo5 development
Home-page: http://blog.pyjama.bressure.net
Author: Thierry Bressure
Author-email: pyjama@bressure.net
License: UNKNOWN
Download-URL: http://pyjama.bressure.net
Platform: UNKNOWN
Classifier: Development Status :: 2 - Pre-Alpha
Classifier: Environment :: Handhelds/PDA's
Classifier: Intended Audience :: End Users/Desktop
Classifier: Intended Audience :: Developers
Classifier: License :: OSI Approved :: GNU Library or Lesser General Public License (LGPL)
Classifier: Operating System :: POSIX :: Linux
Classifier: Programming Language :: Python
